[
  {
    "lawCode": "IS",
    "lawName": "İş Kanunu",
    "articleNumber": "2",
    "title": "Kapsam",
    "text": "Bu Kanun, 4 üncü maddede tanımlanan işçiler ile işverenler arasındaki iş ilişkilerine uygulanır. Deniz ve hava taşıma işleri, tarım işleri vb. kanunda özel düzenlemeye tabidir.",
    "keywords": [
      "kapsam",
      "kanun",
      "üncü",
      "maddede",
      "tanımlanan",
      "işçiler",
      "ile",
      "işverenler"
    ],
    "legalArea": "İş Hukuku"
  },
  {
    "lawCode": "IS",
    "lawName": "İş Kanunu",
    "articleNumber": "8",
    "title": "İşçi",
    "text": "Bir iş sözleşmesine dayanarak çalışan gerçek kişiye işçi denir.",
    "keywords": [
      "şçi",
      "bir",
      "sözleşmesine",
      "dayanarak",
      "çalışan",
      "gerçek",
      "kişiye",
      "işçi"
    ],
    "legalArea": "İş Hukuku"
  },
  {
    "lawCode": "IS",
    "lawName": "İş Kanunu",
    "articleNumber": "3",
    "title": "İşveren",
    "text": "İşçi çalıştıran gerçek veya tüzel kişiye yahut tüzel kişiliği olmayan kurum ve kuruluşlara işveren denir.",
    "keywords": [
      "şveren",
      "şçi",
      "çalıştıran",
      "gerçek",
      "veya",
      "tüzel",
      "kişiye",
      "yahut"
    ],
    "legalArea": "İş Hukuku"
  },
  {
    "lawCode": "IS",
    "lawName": "İş Kanunu",
    "articleNumber": "63",
    "title": "Haftalık çalışma süresi",
    "text": "Genel kural olarak haftalık çalışma süresi kırk saattir. Aksi kararlaştırılmadıkça bu süre, işyerlerinde haftanın çalışılan günlerine eşit ölçüde bölünerek uygulanır.",
    "keywords": [
      "haftalık",
      "çalışma",
      "süresi",
      "genel",
      "kural",
      "olarak",
      "kırk",
      "saattir"
    ],
    "legalArea": "İş Hukuku"
  },
  {
    "lawCode": "IS",
    "lawName": "İş Kanunu",
    "articleNumber": "113",
    "title": "Kıdem tazminatı",
    "text": "Belirli süreli iş sözleşmesinin süresi biten veya belirsiz süreli iş sözleşmesinin işveren tarafından feshedilen işçi, en az bir yıl çalışmış olması hâlinde kıdem tazminatına hak kazanır.",
    "keywords": [
      "kıdem",
      "tazminatı",
      "belirli",
      "süreli",
      "sözleşmesinin",
      "süresi",
      "biten",
      "veya"
    ],
    "legalArea": "İş Hukuku"
  },
  {
    "lawCode": "IS",
    "lawName": "İş Kanunu",
    "articleNumber": "17",
    "title": "Fesih",
    "text": "İş sözleşmesi, tarafların karşılıklı anlaşması veya tek taraflı fesih ile sona erer. Haklı fesih nedenleri kanunda düzenlenir; fesih bildirimi yazılı yapılır.",
    "keywords": [
      "fesih",
      "sözleşmesi",
      "tarafların",
      "karşılıklı",
      "anlaşması",
      "veya",
      "tek",
      "taraflı"
    ],
    "legalArea": "İş Hukuku"
  }
]